[
    {
        "bill_number": "MeitY-2026-01",
        "title": "Digital Personal Data Protection (DPDP) Implementation Rules",
        "status": "Active",
        "status_label": "Notification Issued",
        "ministry": "Electronics & IT",
        "ministry_slug": "meity",
        "date": "2026-05-21",
        "summary": "Rules outlining compliance mandates, consent frameworks, and penalty thresholds for data fiduciaries."
    },
    {
        "bill_number": "Cabinet-2026-14",
        "title": "National Quantum Mission (NQM) Operational Guidelines",
        "status": "Approved",
        "status_label": "Cabinet Clearance",
        "ministry": "Science & Technology",
        "ministry_slug": "dst",
        "date": "2026-05-21",
        "summary": "Release of structured funding and resource allocation metrics for public-private research hubs across states."
    }
]